tensorcro/__init__.py
tensorcro/__special__.py
tensorcro/slcro.py
tensorcro/replay/__init__.py
tensorcro/replay/watch_replay.py
tensorcro/substrates/__init__.py
tensorcro/substrates/mutation.py
tensorcro/substrates/substrate.py
tensorcro/substrates/algorithms/__init__.py
tensorcro/substrates/algorithms/differential_search.py
tensorcro/substrates/algorithms/harmony_search.py
tensorcro/substrates/algorithms/random_search.py
tensorcro/substrates/crossovers/__init__.py
tensorcro/substrates/crossovers/blxalpha_crossover.py
tensorcro/substrates/crossovers/gaussian_crossover.py
tensorcro/substrates/crossovers/masked_crossover.py
tensorcro/substrates/crossovers/multipoint_crossover.py
tensorcro/substrates/crossovers/uniform_crossover.py
tensorcro-1.2.1.dist-info/METADATA
tensorcro-1.2.1.dist-info/WHEEL
tensorcro-1.2.1.dist-info/top_level.txt
tensorcro-1.2.1.dist-info/RECORD
