Metadata-Version: 2.1
Name: tensorcro
Version: 1.2.1
Summary: TensorCRO: A Tensorflow-based implementation of the Coral Reef Optimization algorithm.
Home-page: https://github.com/iTzAlver/tensorcro.git
Author: Palomo-Alonso, Alberto
Author-email: a.palomo@edu.uah
Project-URL: Documentation, https://htmlpreview.github.io/?https://github.com/iTzAlver/tensorcro/blob/main/
Project-URL: Bug Reports, https://github.com/iTzAlver/tensorcro/issues
Project-URL: Source Code, https://github.com/iTzAlver/tensorcro.git
Keywords: deeplearning,ml,api,optimization,heuristic
Classifier: Development Status :: 5 - Production/Stable
Classifier: Topic :: Software Development :: Build Tools
Classifier: Programming Language :: Python :: 3
Classifier: Operating System :: OS Independent
Classifier: License :: OSI Approved :: Apache Software License
Requires-Python: >=3.8
Requires-Dist: numpy (>=1.23.5)
Requires-Dist: tensorflow (>=2.12.0)
Requires-Dist: matplotlib (>=3.7.1)
Requires-Dist: pandas (>=2.0.0)
Provides-Extra: dev
Requires-Dist: check-manifest ; extra == 'dev'
